CHANGELOG.md
nwa/cli/__main__.py
nwa/cli/base_command.py
nwa/cli/commands/__init__.py
nwa/cli/commands/controllability.py
nwa/cli/commands/intervention.py
nwa/cli/commands/network.py
nwa/cli/commands/outcome.py
nwa/cli/commands/xcs.py
nwa/logger.py
nwa/settings.py
nwa-0.0.1.dist-info/entry_points.txt
nwa-0.0.1.dist-info/LICENSE
nwa-0.0.1.dist-info/WHEEL
nwa-0.0.1.dist-info/METADATA
nwa-0.0.1.dist-info/RECORD
