Metadata-Version: 2.1
Name: nwa
Version: 0.0.1
Summary: A collection of network analyses
Home-page: https://github.com/nichelia/nwa
License: MIT
Keywords: python,network,analysis
Author: Nicholas Elia
Author-email: me@nichelia.com
Maintainer: Nicholas Elia
Maintainer-email: me@nichelia.com
Requires-Python: >=3.7,<4.0
Classifier: License :: OSI Approved :: MIT License
Classifier: Programming Language :: Python :: 3
Classifier: Programming Language :: Python :: 3.7
Classifier: Programming Language :: Python :: 3.8
Requires-Dist: aiodns (>=2.0,<3.0)
Requires-Dist: aiohttp (>=3.6,<4.0)
Requires-Dist: asyncio (>=3.4,<4.0)
Requires-Dist: matplotlib (>=3.1,<4.0)
Requires-Dist: networkx (>=2.4,<3.0)
Requires-Dist: pyyaml (>=5.3,<6.0)
Project-URL: Repository, https://github.com/nichelia/nwa
